netext-0.3.1.dist-info/METADATA
netext-0.3.1.dist-info/WHEEL
netext-0.3.1.dist-info/licenses/LICENSE
netext.libs/libgcc_s-e52197c3.so.1
netext/node_rendering/buffers.py
netext/geometry/magnet.py
netext/geometry/point.py
netext/geometry/region.py
netext/geometry/size.py
netext/geometry/__init__.py
netext/edge_rasterizer.py
netext/console_graph.py
netext/edge_routing/modes.py
netext/edge_routing/edge.py
netext/edge_routing/route.py
netext/edge_routing/node_anchors.py
netext/edge_routing/__init__.py
netext/_core.pyi
netext/testing/assertions.py
netext/rendering/segment_buffer.py
netext/rendering/__init__.py
netext/node_rasterizer.py
netext/layout_engines.py
netext/textual_widget/widget.py
netext/textual_widget/__init__.py
netext/buffer_renderer.py
netext/properties/arrow_tips.py
netext/properties/style.py
netext/properties/shape.py
netext/properties/edge.py
netext/properties/node.py
netext/properties/__init__.py
netext/__init__.py
netext/edge_rendering/arrow_tips.py
netext/edge_rendering/modes.py
netext/edge_rendering/buffer.py
netext/edge_rendering/__init__.py
netext/edge_rendering/path_rasterizer.py
netext/shapes/shape.py
netext/shapes/__init__.py
netext/shapes/box.py
netext/_core.abi3.so
netext-0.3.1.dist-info/RECORD
