Metadata-Version: 2.4
Name: netext
Version: 0.3.1
Requires-Dist: rich>=13
Requires-Dist: networkx~=3.0
Requires-Dist: cachetools>=5.3.0
Requires-Dist: typing-extensions>=4.12.2
Requires-Dist: textual>=1 ; extra == 'textual'
Provides-Extra: textual
License-File: LICENSE
Summary: A graph (network) rendering library for the terminal.
Keywords: network,graph,terminal,rich
Author-email: Malte Klemm <me@malteklemm.de>
License: MIT Licence
Requires-Python: >=3.10
Project-URL: Source code, https://github.com/mahrz24/netext
Project-URL: Documentation, https://mahrz24.github.io/netext/
